fluid/__init__.py
fluid/domain/Karthiks_Model_Engine.py
fluid/domain/__init__.py
KarthiksModelEngine-0.7.8.dist-info/LICENSE.rst
KarthiksModelEngine-0.7.8.dist-info/METADATA
KarthiksModelEngine-0.7.8.dist-info/WHEEL
KarthiksModelEngine-0.7.8.dist-info/top_level.txt
KarthiksModelEngine-0.7.8.dist-info/RECORD
