Metadata-Version: 2.1
Name: KarthiksModelEngine
Version: 0.7.8
Summary: Just an another Python Package with SuperMachine Abilities
Home-page: https://github.com/import666/Karthiks_Model_Engine
Author: Karthik Devalla
Author-email: ihatecoding666@gmail.com
License: UNKNOWN
Keywords: Automl,Supervised Learning
Platform: UNKNOWN
Classifier: Programming Language :: Python :: 3
Classifier: License :: OSI Approved :: MIT License
Classifier: Operating System :: OS Independent
Requires-Python: >=3.8
License-File: LICENSE.rst
Requires-Dist: pandas
Requires-Dist: numpy
Requires-Dist: scikit-learn
Requires-Dist: scikit-optimize
Requires-Dist: matplotlib
Requires-Dist: xgboost
Requires-Dist: h5py
Requires-Dist: gdown
